<?xml version="1.0" encoding="UTF-8" ?>
<!-- No copyright or license for configuration file, details here are not considered a creative work. -->
<moqui-conf xmlns:xsi="http://www.w3.org/2001/XMLSchema-instance"
        xsi:noNamespaceSchemaLocation="http://moqui.org/xsd/moqui-conf-1.6.xsd">

    <tools enable-elasticsearch="true" enable-camel="true"/>

    <server-stats stats-skip-condition="pathInfo?.startsWith('/rpc') || pathInfo?.startsWith('/rest') || pathInfo?.startsWith('/status')">
        <artifact-stats type="screen" persist-bin="true" persist-hit="true"/>
        <artifact-stats type="screen-content" persist-bin="true" persist-hit="true"/>
        <artifact-stats type="transition" persist-bin="true" persist-hit="true"/>
        <artifact-stats type="service" persist-bin="true" persist-hit="false"/>
        <artifact-stats type="entity" persist-bin="false"/>
    </server-stats>

    <webapp-list>
        <!-- NOTE: when you set https-enabled="true" make sure to set the http-port and https-port attributes -->
        <webapp name="webroot" http-port="" http-host=""
                https-port="" https-host="" https-enabled="false"
                require-session-token="true">
            <root-screen host=".*" location="component://webroot/screen/webroot.xml"/>
        </webapp>
    </webapp-list>

    <screen-facade boundary-comments="false"/>

    <entity-facade crypt-pass="MoquiDefaultPassword:CHANGEME">
        <!-- add datasource elements here to configure databases -->
    </entity-facade>

    <repository-list>
        <!-- <repository name="main" location="http://localhost:8081/rmi" type="rmi" workspace="default"
                    username="admin" password="admin"/> -->
    </repository-list>
</moqui-conf>
